pmutils/__init__.py
pmutils/file_utils/__init__.py
pmutils/file_utils/file_util.py
pmutils/json_utlis/__init__.py
pmutils/json_utlis/json_utlis.py
pmutils/system_utils/__init__.py
pmutils/system_utils/keyboard_util.py
pmutils/system_utils/mouse_util.py
pmutils/system_utils/regedit_util.py
pmutils/system_utils/system_util.py
pmutils/system_utils/terminal_util.py
pmutils/system_utils/volume_util.py
pmutils-0.0.6.dist-info/METADATA
pmutils-0.0.6.dist-info/WHEEL
pmutils-0.0.6.dist-info/top_level.txt
pmutils-0.0.6.dist-info/RECORD
